sellapp/__init__.py
sellapp/sellapp.py
sellapp-1.0.4.dist-info/METADATA
sellapp-1.0.4.dist-info/WHEEL
sellapp-1.0.4.dist-info/top_level.txt
sellapp-1.0.4.dist-info/RECORD
