Metadata-Version: 2.1
Name: sellapp
Version: 1.0.4
Summary: Python SDK for sell.app
Project-URL: Homepage, https://github.com/qoft/sellapp.py
Keywords: sell.app,sellapp
Requires-Python: >=3.7
Requires-Dist: httpx
